pyaudacity/__init__.py
pyaudacity_x-0.1.4.dist-info/METADATA
pyaudacity_x-0.1.4.dist-info/WHEEL
pyaudacity_x-0.1.4.dist-info/top_level.txt
pyaudacity_x-0.1.4.dist-info/RECORD
